scc4onnx/__init__.py
scc4onnx/__main__.py
scc4onnx/onnx_input_order_converter.py
scc4onnx-1.0.7.dist-info/licenses/LICENSE
scc4onnx-1.0.7.dist-info/METADATA
scc4onnx-1.0.7.dist-info/WHEEL
scc4onnx-1.0.7.dist-info/entry_points.txt
scc4onnx-1.0.7.dist-info/top_level.txt
scc4onnx-1.0.7.dist-info/RECORD
