Metadata-Version: 2.4
Name: scc4onnx
Version: 1.0.7
Summary: Very simple NCHW and NHWC conversion tool for ONNX. Change to the specified input order for each and every input OP. Also, change the channel order of RGB and BGR. Simple Channel Converter for ONNX. Simple Channel Conversion for ONNX.
Home-page: https://github.com/PINTO0309/scc4onnx
Author: Katsuya Hyodo
Author-email: rmsdh122@yahoo.co.jp
License: MIT License
Platform: linux
Platform: unix
Requires-Python: >=3.6
License-File: LICENSE
Dynamic: author
Dynamic: author-email
Dynamic: description
Dynamic: description-content-type
Dynamic: home-page
Dynamic: license
Dynamic: license-file
Dynamic: platform
Dynamic: requires-python
Dynamic: summary
